README.md
setup.cfg
setup.py
krider/__init__.py
krider/bot_config.py
krider/main.py
krider/stock_data_provider.py
krider/stock_store.py
krider/ticker_data.py
krider/notifications/__init__.py
krider/notifications/console_notifier.py
krider/notifications/reddit_notifier.py
krider/tasks/__init__.py
krider/tasks/ema_cross_over.py
krider/tasks/gainers_losers.py
krider/tasks/historical_data_downloader.py
krider/tasks/volume_analysis.py
krider/utils/__init__.py
krider/utils/log_helper.py
krider/utils/report_generator.py
krider/utils/timing_decorator.py
stock_rider.egg-info/PKG-INFO
stock_rider.egg-info/SOURCES.txt
stock_rider.egg-info/dependency_links.txt
stock_rider.egg-info/entry_points.txt
stock_rider.egg-info/not-zip-safe
stock_rider.egg-info/requires.txt
stock_rider.egg-info/top_level.txt