Metadata-Version: 1.1
Name: stock-rider
Version: 0.12.20201121
Summary: Stock Rider
Home-page: https://github.com/namuan/stock-rider
Author: DeskRiders Dev
Author-email: me@deskriders.dev
License: MIT
Platform: any
Classifier: Development Status :: 4 - Beta
Classifier: Environment :: Console
Classifier: Intended Audience :: Developers
Classifier: License :: OSI Approved :: BSD License
Classifier: Operating System :: POSIX
Classifier: Operating System :: MacOS
Classifier: Operating System :: Unix
Classifier: Operating System :: Microsoft :: Windows
Classifier: Programming Language :: Python :: 3
Classifier: Topic :: Software Development :: Libraries :: Python Modules
